stashyio
