Metadata-Version: 1.1
Name: stashyio
Version: 0.0.2
Summary: The Stashy SDK for Python
Home-page: https://github.com/snclucas/stashy_python
Author: Stashy
Author-email: dev@stashyio.io
License: MIT
Download-URL: https://github.com/snclucas/stashy_python
Platform: UNKNOWN
Classifier: Development Status :: 4 - Beta
Classifier: Intended Audience :: Developers
Classifier: Natural Language :: English
Classifier: Programming Language :: Python
Classifier: Programming Language :: Python :: 2.6
Classifier: Programming Language :: Python :: 2.7
Classifier: Programming Language :: Python :: 3
Classifier: Programming Language :: Python :: 3.3
Classifier: Programming Language :: Python :: 3.4
Classifier: Programming Language :: Python :: 3.5
Classifier: Programming Language :: Python :: 3.6
